mcp_atlassian/__init__.py
mcp_atlassian/server.py
mcp_atlassian/confluence/__init__.py
mcp_atlassian/confluence/client.py
mcp_atlassian/confluence/comments.py
mcp_atlassian/confluence/config.py
mcp_atlassian/confluence/pages.py
mcp_atlassian/confluence/search.py
mcp_atlassian/confluence/spaces.py
mcp_atlassian/jira/__init__.py
mcp_atlassian/jira/attachments.py
mcp_atlassian/jira/boards.py
mcp_atlassian/jira/client.py
mcp_atlassian/jira/comments.py
mcp_atlassian/jira/config.py
mcp_atlassian/jira/epics.py
mcp_atlassian/jira/fields.py
mcp_atlassian/jira/formatting.py
mcp_atlassian/jira/issues.py
mcp_atlassian/jira/projects.py
mcp_atlassian/jira/search.py
mcp_atlassian/jira/transitions.py
mcp_atlassian/jira/users.py
mcp_atlassian/jira/utils.py
mcp_atlassian/jira/worklog.py
mcp_atlassian/models/__init__.py
mcp_atlassian/models/base.py
mcp_atlassian/models/confluence.py
mcp_atlassian/models/constants.py
mcp_atlassian/models/jira.py
mcp_atlassian/preprocessing/__init__.py
mcp_atlassian/preprocessing/base.py
mcp_atlassian/preprocessing/confluence.py
mcp_atlassian/preprocessing/jira.py
mcp_atlassian/utils/__init__.py
mcp_atlassian/utils/io.py
mcp_atlassian/utils/logging.py
mcp_atlassian/utils/ssl.py
mcp_atlassian/utils/urls.py
ff_mcp_atlassian-0.4.0.dist-info/METADATA
ff_mcp_atlassian-0.4.0.dist-info/WHEEL
ff_mcp_atlassian-0.4.0.dist-info/entry_points.txt
ff_mcp_atlassian-0.4.0.dist-info/licenses/LICENSE
ff_mcp_atlassian-0.4.0.dist-info/RECORD
